flask_socketio/__init__.py
flask_socketio/namespace.py
flask_socketio/test_client.py
Flask_SocketIO-5.4.1.dist-info/LICENSE
Flask_SocketIO-5.4.1.dist-info/METADATA
Flask_SocketIO-5.4.1.dist-info/WHEEL
Flask_SocketIO-5.4.1.dist-info/top_level.txt
Flask_SocketIO-5.4.1.dist-info/RECORD
