Metadata-Version: 2.1
Name: Flask-SocketIO
Version: 5.4.1
Summary: Socket.IO integration for Flask applications
Author-email: Miguel Grinberg <miguel.grinberg@gmail.com>
Project-URL: Homepage, https://github.com/miguelgrinberg/flask-socketio
Project-URL: Bug Tracker, https://github.com/miguelgrinberg/flask-socketio/issues
Classifier: Environment :: Web Environment
Classifier: Intended Audience :: Developers
Classifier: Programming Language :: Python :: 3
Classifier: License :: OSI Approved :: MIT License
Classifier: Operating System :: OS Independent
Requires-Python: >=3.6
License-File: LICENSE
Requires-Dist: Flask>=0.9
Requires-Dist: python-socketio>=5.0.2
Provides-Extra: docs
Requires-Dist: sphinx; extra == "docs"
